{
    "batchSize": 128,
    "number_of_epochs": 1000,
    "last_executing_epoch_index": 0,
    "last_executed_batch_index": -1,
    "last_completed": true,
    "randomIndexList": [
        3121,
        2484,
        2782,
        471,
        1053,
        2043,
        852,
        238,
        300,
        779,
        2546,
        376,
        2544,
        2354,
        199,
        304,
        2654,
        873,
        1824,
        213,
        200,
        1490,
        1264,
        1714,
        2731,
        1046,
        2191,
        2361,
        1632,
        2885,
        1965,
        1178,
        1589,
        646,
        1799,
        2171,
        2679,
        163,
        787,
        673,
        2156,
        143,
        1261,
        3237,
        99,
        2737,
        893,
        1972,
        2584,
        1064,
        874,
        2445,
        1511,
        220,
        2365,
        1169,
        18,
        2589,
        2565,
        2541,
        2640,
        2342,
        2384,
        1029,
        2674,
        2992,
        2226,
        2276,
        330,
        152,
        1501,
        1818,
        2735,
        1438,
        108,
        1956,
        648,
        2583,
        1173,
        1887,
        74,
        3062,
        2320,
        2490,
        2708,
        735,
        2368,
        2068,
        575,
        712,
        2475,
        576,
        1736,
        2838,
        1167,
        2233,
        2967,
        1553,
        1881,
        3004,
        1181,
        373,
        2526,
        1200,
        1862,
        709,
        3008,
        581,
        350,
        1568,
        1516,
        2614,
        3264,
        2203,
        2598,
        2540,
        647,
        2849,
        2409,
        785,
        1009,
        2671,
        2251,
        1291,
        1556,
        45,
        3244,
        1390,
        1579,
        1493,
        2025,
        2494,
        3175,
        1229,
        2239,
        2914,
        2061,
        2200,
        2111,
        2536,
        1065,
        1216,
        2098,
        727,
        516,
        68,
        1791,
        1275,
        1966,
        1279,
        1020,
        1858,
        3177,
        2325,
        360,
        2926,
        2528,
        1314,
        2809,
        69,
        1724,
        446,
        3011,
        1400,
        1097,
        1518,
        1914,
        2397,
        343,
        2149,
        1226,
        1891,
        1794,
        1076,
        35,
        2516,
        3269,
        210,
        1926,
        1412,
        1995,
        400,
        1213,
        1151,
        1648,
        618,
        777,
        2698,
        2310,
        1574,
        2307,
        1232,
        837,
        3034,
        2711,
        3052,
        3006,
        1497,
        2727,
        249,
        2263,
        81,
        2478,
        2224,
        780,
        1864,
        2331,
        3039,
        270,
        1452,
        1707,
        1641,
        1077,
        2808,
        2124,
        3252,
        1983,
        1838,
        638,
        450,
        2039,
        1359,
        1080,
        1682,
        458,
        2065,
        502,
        2014,
        574,
        1294,
        1340,
        2718,
        510,
        440,
        481,
        342,
        250,
        675,
        183,
        1931,
        3119,
        291,
        1927,
        1919,
        2975,
        2504,
        2781,
        2909,
        1479,
        2613,
        790,
        2830,
        2901,
        2691,
        1773,
        1669,
        1693,
        946,
        461,
        2370,
        1424,
        3205,
        1299,
        919,
        767,
        3227,
        1584,
        293,
        2533,
        1364,
        140,
        1958,
        3021,
        2810,
        3184,
        1567,
        3059,
        2774,
        680,
        865,
        2041,
        2441,
        1827,
        89,
        3179,
        2610,
        1467,
        3001,
        810,
        314,
        2769,
        2223,
        892,
        2109,
        1464,
        463,
        1161,
        747,
        641,
        782,
        608,
        278,
        1915,
        1666,
        1599,
        2558,
        17,
        2947,
        1153,
        2673,
        924,
        1781,
        251,
        197,
        1005,
        2889,
        606,
        2835,
        625,
        1865,
        3219,
        3087,
        2567,
        3242,
        1996,
        987,
        2840,
        3168,
        2006,
        623,
        3210,
        9,
        78,
        1536,
        1027,
        1357,
        1831,
        162,
        3045,
        313,
        2622,
        269,
        2283,
        2060,
        2899,
        3236,
        246,
        2452,
        1368,
        3142,
        97,
        2271,
        2549,
        3221,
        1720,
        1867,
        1859,
        2449,
        824,
        2115,
        2751,
        2630,
        2465,
        1055,
        2392,
        573,
        2215,
        928,
        532,
        1220,
        3013,
        2492,
        2881,
        1315,
        1223,
        1968,
        2401,
        2053,
        1620,
        750,
        1387,
        1930,
        2938,
        2074,
        3048,
        2683,
        2426,
        282,
        1888,
        2179,
        2139,
        2942,
        615,
        734,
        2553,
        521,
        319,
        1503,
        1694,
        2304,
        1778,
        1105,
        929,
        76,
        355,
        2758,
        1346,
        2760,
        295,
        3081,
        1184,
        2261,
        1011,
        1999,
        1422,
        1067,
        136,
        2085,
        2438,
        364,
        1853,
        138,
        2480,
        3250,
        1266,
        1353,
        2832,
        2326,
        518,
        619,
        507,
        1211,
        1041,
        2963,
        889,
        90,
        2844,
        1195,
        918,
        1942,
        1533,
        1474,
        597,
        826,
        1940,
        449,
        2008,
        3138,
        1742,
        359,
        1239,
        1321,
        2872,
        3276,
        2186,
        1418,
        2740,
        541,
        3224,
        2971,
        434,
        2948,
        1110,
        956,
        1815,
        1285,
        1886,
        746,
        708,
        227,
        2424,
        3118,
        1570,
        2339,
        3108,
        2581,
        3053,
        2042,
        1699,
        2979,
        178,
        1647,
        856,
        1807,
        2891,
        1017,
        788,
        1705,
        1089,
        1048,
        539,
        2883,
        2761,
        2067,
        194,
        327,
        2730,
        1534,
        748,
        554,
        2666,
        2274,
        781,
        561,
        1115,
        1278,
        555,
        1455,
        2702,
        631,
        258,
        2748,
        828,
        33,
        2532,
        1112,
        809,
        2892,
        1050,
        847,
        1992,
        2886,
        2986,
        1280,
        964,
        774,
        179,
        1423,
        311,
        1217,
        2789,
        1138,
        2950,
        940,
        3105,
        1704,
        1737,
        1482,
        429,
        122,
        3145,
        2743,
        279,
        1163,
        2228,
        1811,
        1627,
        2911,
        2586,
        1132,
        2742,
        1324,
        1212,
        1258,
        2930,
        2374,
        2259,
        2846,
        2556,
        2160,
        2873,
        2580,
        2295,
        193,
        475,
        1484,
        1251,
        1030,
        548,
        415,
        2875,
        1760,
        404,
        2807,
        2100,
        3133,
        1049,
        16,
        1590,
        1837,
        1370,
        325,
        1587,
        1507,
        2063,
        46,
        653,
        1833,
        1152,
        2153,
        591,
        1114,
        517,
        1006,
        1775,
        2004,
        432,
        2551,
        2169,
        2479,
        3246,
        617,
        588,
        252,
        2579,
        2051,
        326,
        3071,
        2641,
        2437,
        3166,
        954,
        2461,
        2090,
        1074,
        2305,
        3254,
        2852,
        980,
        1726,
        901,
        111,
        2878,
        1335,
        2890,
        1068,
        895,
        1172,
        20,
        1309,
        1713,
        996,
        2557,
        1809,
        2382,
        414,
        1374,
        1015,
        2961,
        2229,
        2762,
        2420,
        21,
        1428,
        1310,
        2575,
        2028,
        3153,
        838,
        807,
        1719,
        642,
        1715,
        31,
        1748,
        2324,
        761,
        1505,
        38,
        119,
        528,
        2299,
        1851,
        2087,
        1149,
        40,
        374,
        96,
        1023,
        1998,
        2976,
        362,
        2602,
        340,
        3107,
        1100,
        3061,
        704,
        1884,
        2282,
        2395,
        235,
        3079,
        1025,
        3245,
        1772,
        3190,
        2011,
        3161,
        378,
        1492,
        465,
        165,
        2827,
        3280,
        1821,
        294,
        1660,
        834,
        2552,
        54,
        2923,
        3083,
        209,
        337,
        3267,
        674,
        1317,
        1262,
        2170,
        1188,
        804,
        298,
        421,
        2968,
        2607,
        3100,
        1896,
        79,
        2413,
        1099,
        3206,
        3070,
        2016,
        2741,
        2321,
        202,
        1480,
        2960,
        2035,
        731,
        2700,
        1339,
        925,
        1689,
        2033,
        2161,
        492,
        1249,
        2719,
        1408,
        2190,
        244,
        431,
        1345,
        2943,
        3101,
        1397,
        2946,
        1227,
        1681,
        2151,
        1969,
        384,
        457,
        348,
        3217,
        932,
        973,
        571,
        707,
        1774,
        1787,
        333,
        2591,
        995,
        1806,
        189,
        3218,
        2202,
        1545,
        2300,
        2010,
        2893,
        315,
        1471,
        3263,
        2493,
        599,
        616,
        1381,
        39,
        1738,
        2483,
        3151,
        2847,
        1513,
        3003,
        1565,
        2531,
        2135,
        1651,
        1308,
        1204,
        1635,
        2095,
        823,
        1193,
        858,
        668,
        334,
        1224,
        3265,
        1126,
        725,
        464,
        2457,
        2193,
        133,
        1659,
        403,
        2678,
        1451,
        242,
        1907,
        2623,
        66,
        1805,
        155,
        2001,
        1953,
        2097,
        302,
        1795,
        1959,
        3110,
        2935,
        3171,
        2499,
        123,
        211,
        59,
        2726,
        2057,
        1119,
        3041,
        3207,
        1413,
        1159,
        1414,
        1920,
        2258,
        1453,
        1986,
        389,
        2688,
        2147,
        741,
        2957,
        870,
        523,
        2126,
        1292,
        2338,
        2978,
        3248,
        1332,
        1301,
        2145,
        887,
        2018,
        363,
        491,
        1662,
        1970,
        848,
        3271,
        27,
        2219,
        2538,
        441,
        1982,
        2132,
        351,
        2542,
        792,
        2821,
        1977,
        1951,
        2012,
        390,
        1868,
        1069,
        969,
        1058,
        1037,
        2795,
        125,
        3042,
        3009,
        1461,
        1849,
        721,
        476,
        908,
        650,
        1771,
        1225,
        2554,
        1548,
        798,
        2865,
        1265,
        1002,
        2887,
        2548,
        1984,
        2255,
        2767,
        2903,
        2146,
        438,
        3164,
        765,
        1168,
        2385,
        2418,
        942,
        2996,
        411,
        512,
        1286,
        2047,
        142,
        2798,
        1072,
        2096,
        1901,
        1672,
        3173,
        1836,
        1383,
        2373,
        2723,
        1052,
        2451,
        1274,
        508,
        1564,
        524,
        2618,
        2247,
        419,
        2348,
        509,
        965,
        1063,
        234,
        473,
        905,
        3117,
        435,
        2522,
        992,
        3273,
        3225,
        3016,
        206,
        62,
        2694,
        1460,
        409,
        1658,
        2248,
        3025,
        1094,
        357,
        2606,
        15,
        1298,
        917,
        2766,
        2194,
        2667,
        1257,
        41,
        1668,
        2999,
        1561,
        2303,
        759,
        2235,
        1417,
        935,
        3122,
        2850,
        952,
        503,
        2009,
        1157,
        2293,
        3113,
        562,
        697,
        3146,
        1421,
        1127,
        1723,
        487,
        1923,
        2627,
        1642,
        2757,
        1272,
        1032,
        1869,
        102,
        1363,
        2488,
        660,
        1832,
        2962,
        827,
        1757,
        760,
        1367,
        1790,
        1458,
        1967,
        2040,
        1928,
        2439,
        1638,
        999,
        2214,
        1782,
        961,
        3055,
        655,
        2122,
        2794,
        2419,
        1156,
        1559,
        336,
        2657,
        789,
        1102,
        3126,
        926,
        2864,
        1730,
        1526,
        2131,
        2212,
        2046,
        2804,
        2257,
        301,
        611,
        2569,
        472,
        1766,
        1517,
        1550,
        2005,
        880,
        726,
        2297,
        716,
        875,
        2256,
        2882,
        2675,
        2108,
        2595,
        1230,
        535,
        2023,
        3112,
        2294,
        2218,
        1578,
        690,
        2545,
        60,
        1892,
        2512,
        1419,
        1316,
        2298,
        1835,
        958,
        2662,
        1749,
        1481,
        2965,
        1615,
        308,
        2841,
        268,
        1717,
        2050,
        2337,
        2503,
        2822,
        426,
        2262,
        370,
        2924,
        1573,
        2573,
        1201,
        1608,
        2192,
        116,
        814,
        2724,
        2687,
        2101,
        2173,
        2246,
        3148,
        2442,
        260,
        2272,
        533,
        287,
        3256,
        3046,
        105,
        1555,
        577,
        689,
        349,
        174,
        2508,
        2075,
        1971,
        806,
        2,
        2853,
        382,
        198,
        902,
        527,
        2833,
        2079,
        2894,
        2148,
        2453,
        1432,
        2322,
        3183,
        2837,
        42,
        1162,
        3229,
        2432,
        1107,
        2350,
        1769,
        3201,
        397,
        2155,
        1098,
        1624,
        1355,
        1190,
        1711,
        2064,
        2763,
        485,
        1943,
        990,
        1253,
        2396,
        192,
        1469,
        3096,
        148,
        1779,
        2612,
        1610,
        1379,
        3261,
        1304,
        22,
        1470,
        151,
        2621,
        2277,
        711,
        1673,
        3075,
        418,
        166,
        1500,
        1133,
        652,
        2604,
        3282,
        170,
        800,
        739,
        460,
        526,
        1829,
        1075,
        1143,
        456,
        1535,
        566,
        1394,
        2094,
        821,
        991,
        937,
        1281,
        1750,
        1042,
        601,
        1557,
        570,
        2661,
        630,
        398,
        1003,
        3274,
        2783,
        622,
        2578,
        2268,
        2874,
        2634,
        2105,
        1600,
        2113,
        3104,
        3197,
        1004,
        3186,
        2389,
        736,
        1462,
        2278,
        2527,
        1325,
        1457,
        335,
        2017,
        1852,
        1210,
        2185,
        1687,
        2994,
        1816,
        742,
        1336,
        1377,
        146,
        1950,
        1386,
        1854,
        855,
        453,
        2888,
        1154,
        881,
        2590,
        1468,
        61,
        2162,
        1683,
        2624,
        1644,
        288,
        1626,
        1649,
        3155,
        2404,
        1764,
        2617,
        1378,
        1035,
        139,
        684,
        1847,
        1581,
        2343,
        93,
        1753,
        2427,
        1164,
        2291,
        2069,
        1401,
        563,
        1873,
        2080,
        538,
        2877,
        2144,
        1755,
        1433,
        558,
        962,
        851,
        564,
        2692,
        1798,
        161,
        1661,
        2651,
        141,
        3129,
        2587,
        497,
        1530,
        1356,
        2519,
        1082,
        1073,
        1606,
        1522,
        1250,
        2759,
        1623,
        171,
        989,
        791,
        1621,
        1206,
        1508,
        2316,
        1703,
        762,
        2784,
        2209,
        2287,
        651,
        1362,
        2176,
        1013,
        1499,
        160,
        121,
        602,
        1463,
        3182,
        2241,
        1612,
        2600,
        914,
        2266,
        770,
        714,
        2898,
        2825,
        405,
        903,
        2932,
        984,
        2406,
        936,
        2302,
        145,
        1288,
        2502,
        185,
        2130,
        1389,
        763,
        1539,
        1416,
        2995,
        1221,
        1595,
        1473,
        1646,
        1395,
        715,
        717,
        48,
        2857,
        1296,
        844,
        462,
        1993,
        2505,
        43,
        2358,
        154,
        2227,
        2770,
        187,
        2372,
        1976,
        1252,
        2110,
        567,
        1652,
        1524,
        495,
        2022,
        1129,
        860,
        676,
        2653,
        2826,
        1963,
        514,
        977,
        2092,
        1634,
        2842,
        3132,
        188,
        775,
        1313,
        2220,
        2481,
        2367,
        1547,
        1260,
        55,
        664,
        3068,
        1192,
        1318,
        1060,
        120,
        128,
        1411,
        667,
        1582,
        106,
        2812,
        2765,
        656,
        3157,
        222,
        751,
        939,
        2403,
        1741,
        2292,
        2987,
        663,
        1255,
        2459,
        2854,
        2123,
        2615,
        2633,
        75,
        1577,
        971,
        2103,
        1876,
        603,
        1554,
        467,
        2793,
        1675,
        2237,
        773,
        832,
        2570,
        531,
        2468,
        2706,
        877,
        1585,
        2206,
        232,
        3128,
        2777,
        1785,
        888,
        1214,
        1456,
        1708,
        1338,
        1810,
        1302,
        1569,
        1171,
        50,
        1680,
        1228,
        1987,
        3234,
        2848,
        2286,
        3063,
        2469,
        2980,
        2676,
        1997,
        1044,
        2388,
        1330,
        1734,
        408,
        1973,
        3035,
        693,
        423,
        6,
        3007,
        2806,
        1486,
        1911,
        1365,
        2771,
        1677,
        2955,
        1800,
        2054,
        2555,
        2242,
        1964,
        201,
        2328,
        2637,
        2383,
        356,
        2038,
        1051,
        369,
        2815,
        589,
        1031,
        3038,
        1246,
        276,
        2141,
        1583,
        324,
        2791,
        1767,
        150,
        1113,
        2750,
        1949,
        2414,
        1826,
        2939,
        2333,
        2732,
        305,
        445,
        3158,
        3088,
        173,
        1657,
        1541,
        2997,
        3054,
        2471,
        520,
        2550,
        2362,
        859,
        610,
        1709,
        395,
        115,
        671,
        2184,
        1233,
        2836,
        1496,
        1331,
        3181,
        649,
        878,
        95,
        879,
        1801,
        2958,
        1108,
        2572,
        2317,
        613,
        2335,
        2568,
        1532,
        1817,
        2644,
        2500,
        682,
        1770,
        286,
        506,
        2851,
        3032,
        2380,
        262,
        3095,
        3278,
        519,
        3015,
        2433,
        1489,
        2601,
        2495,
        2594,
        2645,
        590,
        451,
        755,
        941,
        3139,
        329,
        2918,
        1932,
        749,
        1640,
        2959,
        2991,
        3226,
        280,
        1519,
        2059,
        386,
        1348,
        993,
        1732,
        2056,
        3208,
        1664,
        1242,
        1594,
        1601,
        692,
        2152,
        1170,
        2681,
        931,
        947,
        1629,
        2560,
        126,
        365,
        994,
        868,
        2925,
        3159,
        2952,
        2034,
        817,
        1510,
        1343,
        1679,
        107,
        2722,
        3058,
        1597,
        1866,
        1756,
        1739,
        1078,
        839,
        546,
        3017,
        1731,
        2177,
        1667,
        1729,
        2972,
        52,
        86,
        915,
        2823,
        620,
        2345,
        2790,
        1142,
        2410,
        836,
        553,
        906,
        1580,
        1466,
        1086,
        2697,
        1295,
        886,
        2639,
        1712,
        2168,
        354,
        1180,
        2118,
        556,
        3241,
        1733,
        117,
        2628,
        595,
        82,
        3239,
        1551,
        2352,
        3029,
        1671,
        2002,
        2458,
        2655,
        3127,
        525,
        795,
        2230,
        1630,
        3023,
        1436,
        3143,
        801,
        1236,
        1045,
        953,
        1019,
        3097,
        1014,
        1290,
        1603,
        1628,
        545,
        1900,
        645,
        1478,
        568,
        402,
        2523,
        1372,
        3251,
        2990,
        2819,
        73,
        897,
        3268,
        2216,
        1158,
        3067,
        275,
        1194,
        2869,
        854,
        2969,
        955,
        662,
        3033,
        982,
        3199,
        3230,
        2897,
        2576,
        943,
        3027,
        385,
        1342,
        1909,
        1437,
        744,
        2423,
        1812,
        695,
        2288,
        2312,
        2157,
        793,
        1607,
        1740,
        1198,
        2137,
        420,
        1012,
        1122,
        1906,
        2138,
        281,
        3281,
        135,
        70,
        3022,
        778,
        215,
        2507,
        1431,
        2647,
        56,
        265,
        2127,
        2467,
        2019,
        2921,
        2843,
        1636,
        720,
        228,
        47,
        1639,
        2158,
        2444,
        2284,
        2755,
        2907,
        2669,
        1566,
        551,
        2906,
        2656,
        2344,
        3178,
        1701,
        229,
        290,
        3275,
        1789,
        544,
        2535,
        1924,
        2956,
        896,
        1613,
        1735,
        4,
        1273,
        805,
        1656,
        840,
        730,
        3047,
        2332,
        2088,
        2030,
        1243,
        2129,
        394,
        91,
        2036,
        207,
        1803,
        718,
        2313,
        2905,
        3114,
        2070,
        283,
        2198,
        799,
        1525,
        3014,
        2703,
        1863,
        2398,
        2400,
        2693,
        1136,
        1874,
        312,
        3180,
        1897,
        1268,
        922,
        3255,
        3260,
        289,
        3103,
        176,
        2915,
        2648,
        1403,
        3163,
        2062,
        2048,
        1354,
        396,
        1047,
        296,
        1743,
        998,
        3240,
        1402,
        1454,
        1287,
        2603,
        1980,
        2524,
        579,
        738,
        593,
        310,
        243,
        2402,
        1319,
        2802,
        2577,
        2114,
        768,
        318,
        1446,
        1751,
        640,
        1123,
        2236,
        970,
        49,
        1341,
        753,
        2021,
        3135,
        549,
        30,
        3120,
        3086,
        2336,
        2275,
        2530,
        3084,
        3134,
        2491,
        372,
        2037,
        2434,
        1139,
        2253,
        3202,
        3272,
        1686,
        1207,
        3044,
        100,
        1954,
        338,
        104,
        3056,
        416,
        2705,
        3232,
        909,
        1592,
        1933,
        2752,
        1650,
        702,
        2249,
        669,
        190,
        3078,
        701,
        273,
        1878,
        482,
        1702,
        1695,
        1529,
        2319,
        1305,
        686,
        2900,
        607,
        2643,
        1347,
        2477,
        657,
        2181,
        425,
        3258,
        500,
        437,
        2787,
        2588,
        1586,
        1617,
        1024,
        1241,
        2443,
        177,
        2659,
        2739,
        3165,
        1271,
        2213,
        2829,
        1540,
        629,
        728,
        12,
        375,
        843,
        1537,
        2378,
        1399,
        1385,
        2861,
        1625,
        1040,
        3174,
        1415,
        2845,
        949,
        1491,
        1081,
        1293,
        1591,
        1882,
        1921,
        1410,
        1710,
        1910,
        2820,
        849,
        11,
        3140,
        2323,
        2314,
        3160,
        885,
        2537,
        724,
        2582,
        899,
        410,
        2154,
        2772,
        2440,
        797,
        1752,
        37,
        1857,
        466,
        459,
        1908,
        483,
        3005,
        933,
        737,
        2860,
        87,
        1398,
        2334,
        1061,
        835,
        1670,
        1899,
        1611,
        1523,
        1676,
        1828,
        1459,
        1085,
        1934,
        2884,
        10,
        2415,
        72,
        1160,
        130,
        3012,
        2205,
        1718,
        1485,
        1303,
        2269,
        2463,
        968,
        530,
        1495,
        1371,
        1311,
        2818,
        3,
        722,
        1376,
        2509,
        316,
        2597,
        572,
        1022,
        2032,
        444,
        494,
        513,
        2116,
        2119,
        2225,
        1842,
        501,
        1985,
        1334,
        1215,
        5,
        1938,
        1095,
        1542,
        584,
        417,
        3066,
        149,
        592,
        3144,
        1472,
        3196,
        88,
        3209,
        2805,
        1096,
        2306,
        1688,
        224,
        2375,
        2855,
        2052,
        442,
        2210,
        2330,
        477,
        1384,
        2117,
        1549,
        658,
        985,
        175,
        1021,
        732,
        2387,
        1118,
        825,
        478,
        907,
        515,
        1155,
        2895,
        1945,
        1747,
        2868,
        866,
        1848,
        557,
        1602,
        2954,
        1219,
        248,
        634,
        679,
        1488,
        1962,
        740,
        1616,
        1498,
        2072,
        2521,
        871,
        1935,
        2539,
        1208,
        2121,
        2055,
        3031,
        1130,
        2778,
        2476,
        3172,
        2931,
        3080,
        1685,
        2966,
        1361,
        1895,
        124,
        2366,
        1267,
        2684,
        1066,
        196,
        3069,
        1758,
        2902,
        2824,
        2574,
        2779,
        2831,
        600,
        1144,
        1877,
        391,
        1442,
        2896,
        2411,
        1322,
        2945,
        1948,
        3154,
        743,
        1426,
        2814,
        2446,
        2208,
        1761,
        2417,
        1238,
        144,
        307,
        710,
        480,
        2563,
        594,
        1912,
        912,
        670,
        1754,
        1885,
        2497,
        112,
        2754,
        1079,
        118,
        2045,
        1819,
        2024,
        339,
        813,
        2867,
        203,
        3249,
        1784,
        393,
        2721,
        2631,
        967,
        1889,
        1062,
        2940,
        24,
        2564,
        951,
        983,
        988,
        236,
        786,
        1663,
        2785,
        2792,
        1134,
        930,
        1358,
        2359,
        2120,
        2270,
        1546,
        3085,
        2221,
        2003,
        978,
        2801,
        1979,
        2547,
        1861,
        2260,
        231,
        1543,
        53,
        2713,
        1448,
        1645,
        802,
        2695,
        3130,
        665,
        392,
        2605,
        3051,
        271,
        580,
        1297,
        891,
        1277,
        1306,
        696,
        766,
        1684,
        3092,
        699,
        2474,
        3222,
        864,
        3136,
        2076,
        169,
        2879,
        2454,
        1521,
        253,
        2973,
        2596,
        2000,
        3147,
        2699,
        3270,
        1655,
        157,
        303,
        1237,
        237,
        468,
        511,
        2773,
        890,
        379,
        2416,
        2620,
        134,
        666,
        3257,
        77,
        3176,
        2280,
        2616,
        1351,
        3089,
        559,
        3215,
        1240,
        981,
        3019,
        1844,
        1477,
        587,
        1307,
        1759,
        1796,
        1856,
        850,
        2611,
        3050,
        214,
        2501,
        1091,
        1483,
        3195,
        1576,
        504,
        2462,
        2756,
        2660,
        2264,
        2677,
        2084,
        1449,
        1103,
        255,
        1820,
        1944,
        1637,
        366,
        204,
        377,
        129,
        1000,
        2007,
        2279,
        2729,
        2929,
        948,
        1128,
        543,
        975,
        3125,
        1822,
        1494,
        816,
        2738,
        1282,
        3231,
        2936,
        2083,
        3028,
        1059,
        3049,
        1871,
        2970,
        3099,
        2091,
        2455,
        352,
        284,
        1618,
        756,
        1614,
        3000,
        2470,
        1843,
        223,
        771,
        3124,
        2254,
        1476,
        2876,
        132,
        2608,
        2768,
        2356,
        3262,
        820,
        346,
        1146,
        257,
        167,
        2529,
        1312,
        3194,
        1841,
        698,
        1104,
        1326,
        2863,
        1654,
        2559,
        1562,
        2716,
        2592,
        2082,
        596,
        2800,
        2196,
        2244,
        2912,
        3076,
        1235,
        3036,
        609,
        2355,
        2165,
        1441,
        2951,
        2189,
        2518,
        974,
        1135,
        2180,
        1855,
        58,
        2920,
        2077,
        2734,
        7,
        433,
        1187,
        447,
        184,
        1263,
        3253,
        406,
        1674,
        1405,
        1090,
        2797,
        413,
        2585,
        469,
        639,
        205,
        1531,
        1538,
        2285,
        2871,
        1947,
        44,
        536,
        1520,
        2908,
        1284,
        2922,
        2562,
        2941,
        2803,
        2175,
        2672,
        2405,
        2393,
        2974,
        758,
        219,
        2211,
        3152,
        894,
        1034,
        2599,
        2112,
        36,
        2174,
        2944,
        2473,
        1913,
        1125,
        1174,
        1925,
        164,
        1121,
        1420,
        29,
        2329,
        2862,
        2281,
        3243,
        2204,
        2128,
        1588,
        2919,
        1941,
        921,
        624,
        2927,
        1124,
        2635,
        2308,
        3212,
        2066,
        2745,
        67,
        1333,
        113,
        2430,
        863,
        2386,
        1191,
        1917,
        1259,
        1148,
        1768,
        2143,
        3149,
        972,
        627,
        2140,
        529,
        261,
        1604,
        2425,
        3198,
        2910,
        1946,
        3090,
        1391,
        181,
        1776,
        1504,
        2717,
        2464,
        2460,
        439,
        407,
        1007,
        1893,
        225,
        1898,
        2609,
        542,
        1,
        754,
        1328,
        3211,
        1937,
        1633,
        2858,
        1443,
        1990,
        3018,
        3266,
        3115,
        2086,
        819,
        1880,
        2394,
        3030,
        127,
        1028,
        1001,
        2450,
        672,
        3026,
        2431,
        1380,
        101,
        2715,
        2428,
        1593,
        1846,
        2107,
        272,
        2828,
        1337,
        719,
        614,
        332,
        498,
        489,
        764,
        412,
        677,
        2026,
        2234,
        3024,
        1840,
        2093,
        65,
        2472,
        904,
        3020,
        769,
        1665,
        2988,
        3189,
        1763,
        659,
        2399,
        997,
        98,
        285,
        2273,
        2981,
        2136,
        2736,
        267,
        1609,
        3228,
        808,
        916,
        28,
        2150,
        1375,
        1528,
        114,
        2632,
        550,
        2125,
        2217,
        776,
        1722,
        2238,
        1057,
        2369,
        427,
        2347,
        2391,
        317,
        1407,
        1038,
        2709,
        1745,
        2933,
        3259,
        959,
        3213,
        2680,
        2710,
        3277,
        2346,
        2561,
        218,
        2301,
        1409,
        1016,
        84,
        729,
        1975,
        829,
        186,
        1780,
        882,
        3098,
        1183,
        633,
        1320,
        3010,
        2020,
        2593,
        643,
        1952,
        3214,
        63,
        938,
        1883,
        254,
        2199,
        153,
        2839,
        109,
        1905,
        1839,
        1026,
        3169,
        499,
        862,
        221,
        3203,
        986,
        1721,
        428,
        2485,
        2747,
        306,
        1109,
        1120,
        876,
        2982,
        233,
        867,
        3102,
        2318,
        1981,
        1071,
        3091,
        2058,
        2197,
        681,
        1527,
        2796,
        1434,
        1018,
        883,
        230,
        621,
        496,
        598,
        2619,
        3040,
        217,
        320,
        2670,
        3162,
        1033,
        3111,
        331,
        966,
        2775,
        815,
        2172,
        1802,
        2377,
        2993,
        2682,
        2435,
        266,
        833,
        1746,
        2870,
        1830,
        2664,
        8,
        488,
        1475,
        1245,
        180,
        212,
        399,
        803,
        1622,
        2983,
        2989,
        1218,
        1514,
        299,
        3123,
        2489,
        910,
        3060,
        64,
        2513,
        470,
        381,
        2937,
        2799,
        1087,
        818,
        2250,
        2934,
        2133,
        448,
        2788,
        2690,
        979,
        976,
        1327,
        1797,
        245,
        2296,
        1117,
        1991,
        2159,
        2984,
        2029,
        2817,
        1369,
        683,
        578,
        2376,
        274,
        2663,
        1366,
        2015,
        857,
        2163,
        2642,
        2511,
        57,
        3073,
        1955,
        34,
        2351,
        920,
        3233,
        1393,
        103,
        1700,
        137,
        1092,
        322,
        2311,
        1247,
        1850,
        2764,
        2049,
        605,
        3137,
        547,
        1598,
        1054,
        51,
        1575,
        794,
        1916,
        358,
        713,
        2371,
        586,
        552,
        733,
        3093,
        845,
        2498,
        1450,
        745,
        1140,
        923,
        1957,
        2685,
        3074,
        422,
        1234,
        1440,
        2786,
        2543,
        869,
        341,
        812,
        1903,
        2421,
        1106,
        1196,
        583,
        534,
        226,
        2407,
        1506,
        2245,
        1696,
        811,
        1691,
        1792,
        1728,
        691,
        688,
        147,
        2780,
        1563,
        80,
        1070,
        3065,
        637,
        678,
        239,
        454,
        822,
        1404,
        94,
        2859,
        1786,
        1185,
        159,
        2964,
        1406,
        493,
        705,
        2240,
        1111,
        264,
        1777,
        1860,
        3247,
        1254,
        2341,
        345,
        2290,
        455,
        3150,
        1465,
        1199,
        1994,
        1283,
        0,
        2733,
        3279,
        436,
        110,
        26,
        1176,
        247,
        1804,
        71,
        3185,
        2104,
        1388,
        1765,
        831,
        2880,
        685,
        1175,
        1960,
        1872,
        1425,
        2265,
        1323,
        830,
        2985,
        2164,
        2327,
        3188,
        1572,
        2534,
        2486,
        3043,
        2510,
        700,
        353,
        2629,
        1222,
        1182,
        2201,
        2363,
        2436,
        505,
        1427,
        367,
        2658,
        1509,
        1814,
        3072,
        3077,
        2686,
        2638,
        1922,
        1352,
        2360,
        182,
        328,
        19,
        1131,
        2696,
        368,
        2506,
        2429,
        2816,
        694,
        706,
        172,
        2089,
        1823,
        2183,
        2749,
        1043,
        1690,
        2525,
        1727,
        2916,
        3238,
        560,
        158,
        2707,
        3191,
        452,
        3116,
        861,
        2649,
        2487,
        1269,
        2811,
        796,
        2073,
        277,
        2340,
        1929,
        13,
        853,
        911,
        484,
        1605,
        2031,
        2044,
        2364,
        2834,
        2349,
        1439,
        2720,
        1698,
        842,
        872,
        2776,
        2949,
        3141,
        1008,
        2448,
        23,
        2626,
        3057,
        256,
        1203,
        344,
        1186,
        2517,
        168,
        1487,
        2482,
        934,
        900,
        1890,
        2650,
        944,
        2689,
        612,
        1918,
        1039,
        1150,
        2665,
        292,
        2515,
        2166,
        2289,
        3220,
        3192,
        1137,
        2252,
        1036,
        1289,
        2514,
        85,
        3109,
        913,
        1813,
        1165,
        565,
        2953,
        2178,
        1544,
        1978,
        1653,
        1788,
        636,
        2704,
        443,
        2027,
        92,
        1904,
        240,
        2456,
        1939,
        1558,
        1879,
        1643,
        1179,
        950,
        323,
        2134,
        216,
        957,
        522,
        3187,
        1974,
        1209,
        32,
        3064,
        383,
        1141,
        1697,
        3156,
        2207,
        2520,
        1349,
        1445,
        2725,
        1056,
        1270,
        945,
        1961,
        927,
        1936,
        2412,
        3216,
        2753,
        2231,
        2466,
        2102,
        644,
        1762,
        2232,
        1116,
        1202,
        2071,
        25,
        2646,
        1834,
        540,
        2813,
        1101,
        1444,
        1189,
        1725,
        3037,
        2928,
        884,
        1793,
        2668,
        2357,
        208,
        1619,
        569,
        2390,
        1515,
        2187,
        2081,
        846,
        2728,
        1350,
        191,
        898,
        2408,
        687,
        2636,
        1360,
        2142,
        430,
        2712,
        537,
        259,
        347,
        1512,
        2746,
        195,
        2571,
        14,
        772,
        582,
        2701,
        1783,
        1084,
        3167,
        2566,
        1552,
        1808,
        1875,
        1197,
        1396,
        424,
        309,
        635,
        3200,
        2243,
        585,
        752,
        1166,
        1678,
        1145,
        2866,
        263,
        3235,
        479,
        1231,
        2917,
        388,
        156,
        3170,
        2267,
        2078,
        1177,
        2856,
        131,
        3223,
        757,
        380,
        1988,
        321,
        3193,
        2625,
        784,
        1894,
        490,
        1560,
        654,
        241,
        1329,
        1256,
        2353,
        2106,
        3131,
        387,
        474,
        1244,
        661,
        2188,
        1845,
        2195,
        1392,
        2998,
        2315,
        297,
        1344,
        783,
        2309,
        1205,
        1596,
        1147,
        628,
        1825,
        1429,
        1300,
        3204,
        1373,
        1083,
        703,
        1989,
        1902,
        2447,
        371,
        2381,
        2496,
        2714,
        2977,
        723,
        1435,
        1276,
        1631,
        1716,
        1382,
        1744,
        1692,
        963,
        1571,
        2904,
        2167,
        1010,
        2422,
        1088,
        2744,
        401,
        3082,
        841,
        3106,
        2099,
        1430,
        2013,
        632,
        960,
        2379,
        1093,
        604,
        626,
        2913,
        1447,
        486,
        3094,
        2222,
        2652,
        361,
        1248,
        1502,
        83,
        2182,
        3002,
        1870,
        1706
    ]
}